LICENSE
MANIFEST.in
README.rst
setup.cfg
setup.py
D:/Projekte/Promotion/_workspace/fastchunking/build/rabinkarprh.cpp
fastchunking/__init__.py
fastchunking/benchmark.py
fastchunking/test.py
fastchunking.egg-info/PKG-INFO
fastchunking.egg-info/SOURCES.txt
fastchunking.egg-info/dependency_links.txt
fastchunking.egg-info/requires.txt
fastchunking.egg-info/top_level.txt
lib/__init__.py
lib/characterhash.h
lib/mersennetwister.h
lib/mycharacterhash.h
lib/rabinkarp.cpp
lib/rabinkarp.h
lib/rabinkarp_gen.py
lib/rabinkarpgen.py