Metadata-Version: 1.1
Name: fastchunking
Version: 0.0.3
Summary: Fast chunking library.
Home-page: https://github.com/netleibi/fastchunking
Author: Dominik Leibenger
Author-email: python-fastchunking@mails.dominik-leibenger.de
License: Apache Software License
Keywords: text chunking,SC,static chunking,CDC,content-defined chunking,ML-*,multi-level chunking,ML-SC,ML-CDC,Rabin Karp,rolling hash
Platform: UNKNOWN
Classifier: Development Status :: 2 - Pre-Alpha
Classifier: Intended Audience :: Developers
Classifier: Topic :: Software Development :: Libraries :: Python Modules
Classifier: License :: OSI Approved :: Apache Software License
Classifier: Operating System :: OS Independent
Classifier: Programming Language :: Python :: 3
Classifier: Programming Language :: Python :: 3.5
